data_creator_package/__init__.py
data_creator_package/dataCreator.py
synthetic_data_creator-0.1.0.dist-info/METADATA
synthetic_data_creator-0.1.0.dist-info/WHEEL
synthetic_data_creator-0.1.0.dist-info/top_level.txt
synthetic_data_creator-0.1.0.dist-info/RECORD
