Metadata-Version: 2.1
Name: synthetic-data-creator
Version: 0.1.0
Summary: A package for generating synthetic datasets
Home-page: https://github.com/sarahfy/data_creator_package
Author: Sarah Feyerabend
Author-email: s.feyerabend14@gmx.de
Classifier: Programming Language :: Python :: 3
Classifier: License :: OSI Approved :: MIT License
Classifier: Operating System :: OS Independent
Requires-Dist: numpy
Requires-Dist: pandas
Requires-Dist: enum34
